okx_async/Account.py
okx_async/AsyncAccount.py
okx_async/AsyncBlockTrading.py
okx_async/AsyncConvert.py
okx_async/AsyncCopyTrading.py
okx_async/AsyncEarning.py
okx_async/AsyncFDBroker.py
okx_async/AsyncFunding.py
okx_async/AsyncGrid.py
okx_async/AsyncMarketData.py
okx_async/AsyncNDBroker.py
okx_async/AsyncPublicData.py
okx_async/AsyncSpreadTrading.py
okx_async/AsyncStatus.py
okx_async/AsyncSubAccount.py
okx_async/AsyncTrade.py
okx_async/AsyncTradingData.py
okx_async/BlockTrading.py
okx_async/Convert.py
okx_async/CopyTrading.py
okx_async/Earning.py
okx_async/FDBroker.py
okx_async/Funding.py
okx_async/Grid.py
okx_async/MarketData.py
okx_async/NDBroker.py
okx_async/PublicData.py
okx_async/SpreadTrading.py
okx_async/Status.py
okx_async/SubAccount.py
okx_async/Trade.py
okx_async/TradingData.py
okx_async/__init__.py
okx_async/asyncClient.py
okx_async/client.py
okx_async/consts.py
okx_async/exceptions.py
okx_async/utils.py
okx_async/websocket/WsClientFactory.py
okx_async/websocket/WsClientProtocol.py
okx_async/websocket/WsConnectManager.py
okx_async/websocket/WsLoginFactory.py
okx_async/websocket/WsPrivate.py
okx_async/websocket/WsPublic.py
okx_async/websocket/WsUtils.py
okx_async/websocket/__init__.py
python_okx_async-0.1.1.dist-info/METADATA
python_okx_async-0.1.1.dist-info/WHEEL
python_okx_async-0.1.1.dist-info/top_level.txt
python_okx_async-0.1.1.dist-info/RECORD
