Metadata-Version: 2.1
Name: python-okx-async
Version: 0.1.1
Summary: Python SDK with async support for the OKX v5 API
Home-page: https://okx.com/docs-v5/
Author: CircuitDAO
Author-email: info@circuitdao.com
Classifier: Programming Language :: Python :: 3
Classifier: License :: OSI Approved :: MIT License
Classifier: Operating System :: OS Independent
Requires-Dist: importlib-metadata
Requires-Dist: httpx[http2]
Requires-Dist: keyring
Requires-Dist: requests
Requires-Dist: Twisted
Requires-Dist: pyOpenSSL
